{
  "artifacts": {
    "export_log_path": null,
    "final_render_path": null,
    "preview_render_path": null,
    "render_log_path": null
  },
  "capture_date": "2026-05-26",
  "composition_id": "DaBongBay__20260526",
  "grid_override": null,
  "include": false,
  "layers": [
    {
      "cache_path": "cache/DaBongBay/20260526/PSScene_20260526_034559_38_24da_cloud_0__6806cd752a7a.tif",
      "capture_date": "2026-05-26",
      "capture_time": "03:45:59",
      "cloud_percent": 0.0,
      "layer_id": "PSScene_20260526_034559_38_24da_cloud_0__6806cd752a7a",
      "metadata_source": "filename",
      "metadata_status": "valid",
      "order": 0,
      "source_path": "/home/ongtu/Working/3.ThucTheNgay/examples/20260526/PSScene_20260526_034559_38_24da_cloud_0.tif",
      "visible": true
    },
    {
      "cache_path": "cache/DaBongBay/20260526/PSScene_20260526_034557_35_24da_cloud_0__a219fc2d8ba5.tif",
      "capture_date": "2026-05-26",
      "capture_time": "03:45:57",
      "cloud_percent": 0.0,
      "layer_id": "PSScene_20260526_034557_35_24da_cloud_0__a219fc2d8ba5",
      "metadata_source": "filename",
      "metadata_status": "valid",
      "order": 1,
      "source_path": "/home/ongtu/Working/3.ThucTheNgay/examples/20260526/PSScene_20260526_034557_35_24da_cloud_0.tif",
      "visible": true
    },
    {
      "cache_path": "cache/DaBongBay/20260526/PSScene_20260526_034555_32_24da_cloud_0__0857041f4d3a.tif",
      "capture_date": "2026-05-26",
      "capture_time": "03:45:55",
      "cloud_percent": 0.0,
      "layer_id": "PSScene_20260526_034555_32_24da_cloud_0__0857041f4d3a",
      "metadata_source": "filename",
      "metadata_status": "valid",
      "order": 2,
      "source_path": "/home/ongtu/Working/3.ThucTheNgay/examples/20260526/PSScene_20260526_034555_32_24da_cloud_0.tif",
      "visible": true
    },
    {
      "cache_path": "cache/DaBongBay/20260526/PSScene_20260526_033531_61_252e_cloud_2.0__7bac2dfb1113.tif",
      "capture_date": "2026-05-26",
      "capture_time": "03:35:31",
      "cloud_percent": 2.0,
      "layer_id": "PSScene_20260526_033531_61_252e_cloud_2.0__7bac2dfb1113",
      "metadata_source": "filename",
      "metadata_status": "valid",
      "order": 3,
      "source_path": "/home/ongtu/Working/3.ThucTheNgay/examples/20260526/PSScene_20260526_033531_61_252e_cloud_2.0.tif",
      "visible": true
    },
    {
      "cache_path": "cache/DaBongBay/20260526/PSScene_20260526_033529_39_252e_cloud_2.0__57ce186adbf7.tif",
      "capture_date": "2026-05-26",
      "capture_time": "03:35:29",
      "cloud_percent": 2.0,
      "layer_id": "PSScene_20260526_033529_39_252e_cloud_2.0__57ce186adbf7",
      "metadata_source": "filename",
      "metadata_status": "valid",
      "order": 4,
      "source_path": "/home/ongtu/Working/3.ThucTheNgay/examples/20260526/PSScene_20260526_033529_39_252e_cloud_2.0.tif",
      "visible": true
    },
    {
      "cache_path": "cache/DaBongBay/20260526/PSScene_20260526_033527_17_252e_cloud_0__f05095c5afe5.tif",
      "capture_date": "2026-05-26",
      "capture_time": "03:35:27",
      "cloud_percent": 0.0,
      "layer_id": "PSScene_20260526_033527_17_252e_cloud_0__f05095c5afe5",
      "metadata_source": "filename",
      "metadata_status": "valid",
      "order": 5,
      "source_path": "/home/ongtu/Working/3.ThucTheNgay/examples/20260526/PSScene_20260526_033527_17_252e_cloud_0.tif",
      "visible": true
    }
  ],
  "needs_revalidation": true,
  "notes": "",
  "ready": false,
  "review_order": null,
  "reviewed": false,
  "target_id": "DaBongBay",
  "validation_summary": {
    "error_count": 0,
    "info_count": 0,
    "last_validated_at": null,
    "warning_count": 0
  },
  "view": {
    "center": [
      112.51449847744355,
      16.05546838652
    ],
    "rotation": 0,
    "scale": 50000
  }
}
